mcpadserver/__init__.py
mcpadserver/client.py
mcpadserver/types.py
mcp_ads_sdk-0.1.0.dist-info/METADATA
mcp_ads_sdk-0.1.0.dist-info/WHEEL
mcp_ads_sdk-0.1.0.dist-info/top_level.txt
mcp_ads_sdk-0.1.0.dist-info/RECORD
