Metadata-Version: 2.4
Name: mcp-ads-sdk
Version: 0.1.0
Summary: Ad monetization SDK for Model Context Protocol servers
Author-email: mcpadserver <hello@mcpadserver.com>
Project-URL: Homepage, https://mcpadserver.com
Project-URL: Documentation, https://mcpadserver.com/docs
Project-URL: Repository, https://github.com/mcpadserver/mcpadserver
Project-URL: Issues, https://github.com/mcpadserver/mcpadserver/issues
Keywords: mcp,model-context-protocol,ads,monetization,ai
Classifier: Development Status :: 3 - Alpha
Classifier: Intended Audience :: Developers
Classifier: Topic :: Software Development :: Libraries :: Python Modules
Classifier: License :: OSI Approved :: MIT License
Classifier: Programming Language :: Python :: 3
Classifier: Programming Language :: Python :: 3.8
Classifier: Programming Language :: Python :: 3.9
Classifier: Programming Language :: Python :: 3.10
Classifier: Programming Language :: Python :: 3.11
Classifier: Programming Language :: Python :: 3.12
Requires-Python: >=3.8
Requires-Dist: httpx>=0.24.0
Requires-Dist: pydantic>=2.0.0
Provides-Extra: dev
Requires-Dist: pytest>=7.0; extra == "dev"
Requires-Dist: black>=23.0; extra == "dev"
Requires-Dist: mypy>=1.0; extra == "dev"
